linuxforhealth/__init__.py
linuxforhealth/packaging/__init__.py
linuxforhealth/packaging/calculator.py
linuxforhealth_packaging-1.0.0.dist-info/LICENSE
linuxforhealth_packaging-1.0.0.dist-info/METADATA
linuxforhealth_packaging-1.0.0.dist-info/WHEEL
linuxforhealth_packaging-1.0.0.dist-info/top_level.txt
linuxforhealth_packaging-1.0.0.dist-info/RECORD
