Metadata-Version: 2.1
Name: linuxforhealth-packaging
Version: 1.0.0
Summary: Sample Integrations for PyPI and GitHub Actions
Home-page: https://github.com/LinuxForHealth/python-packaging
License: Apache 2.0 License
Keywords: linuxforhealth,packaging
Platform: any
Classifier: Development Status :: 5 - Production/Stable
Classifier: License :: OSI Approved :: Apache Software License
Classifier: Operating System :: OS Independent
Classifier: Programming Language :: Python :: 3.9
Classifier: Programming Language :: Python :: 3.10
Classifier: Intended Audience :: Healthcare Industry
Classifier: Intended Audience :: Developers
Classifier: Intended Audience :: Information Technology
Requires-Python: >=3.9
License-File: LICENSE
Provides-Extra: dev
Requires-Dist: pytest (<8.0,>=7.1) ; extra == 'dev'
Requires-Dist: flake8 (<5.0,>=4.0) ; extra == 'dev'
Requires-Dist: autopep8 (<2.0,>=1.6) ; extra == 'dev'
Requires-Dist: isort (<6.0,>=5.10) ; extra == 'dev'
